MANIFEST.in
README.rst
setup.cfg
setup.py
eccehomo/__init__.py
eccehomo/app.py
eccehomo/fields.py
eccehomo/settings.py
eccehomo/utils.py
eccehomo.egg-info/PKG-INFO
eccehomo.egg-info/SOURCES.txt
eccehomo.egg-info/dependency_links.txt
eccehomo.egg-info/entry_points.txt
eccehomo.egg-info/requires.txt
eccehomo.egg-info/top_level.txt
requirements/base.txt