Metadata-Version: 1.1
Name: eccehomo
Version: 0.1.3
Summary: Micro application to serve images with customized cropping
Home-page: https://github.com/dictget/ecce-homo
Author: DictGet Team
Author-email: dictget@gmail.com
License: UNKNOWN
Download-URL: https://github.com/dictget/ecce-homo/archive/0.1.3.tar.gz
Platform: UNKNOWN
Classifier: Intended Audience :: Developers
Classifier: Topic :: Software Development :: Libraries :: Python Modules
Classifier: License :: OSI Approved :: MIT License
Classifier: Programming Language :: Python :: 2
Classifier: Programming Language :: Python :: 3
